<profile>

<RTLDesignHierarchy>
<TopModule>
<ModuleName>network_bridge_tcp</ModuleName>
<InstancesList>
<Instance>
<InstName>galapagos_to_tcp_int_U0</InstName>
<ModuleName>galapagos_to_tcp_int</ModuleName>
<ID>180</ID>
</Instance>
<Instance>
<InstName>sessionID_table_stea_U0</InstName>
<ModuleName>sessionID_table_stea</ModuleName>
<ID>226</ID>
</Instance>
<Instance>
<InstName>tcp_to_galapagos_int_U0</InstName>
<ModuleName>tcp_to_galapagos_int</ModuleName>
<ID>248</ID>
</Instance>
<Instance>
<InstName>open_connections_U0</InstName>
<ModuleName>open_connections</ModuleName>
<ID>278</ID>
</Instance>
<Instance>
<InstName>open_port_U0</InstName>
<ModuleName>open_port</ModuleName>
<ID>292</ID>
</Instance>
</InstancesList>
</TopModule>
</RTLDesignHierarchy>

<ModuleInformation>
<Module>
<Name>galapagos_to_tcp_int</Name>
<PerformanceEstimates>
<SummaryOfTimingAnalysis>
<TargetClockPeriod>4.00</TargetClockPeriod>
<ClockUncertainty>0.50</ClockUncertainty>
<TargetInitiationInterval>1</TargetInitiationInterval>
<EstimatedClockPeriod>4.92</EstimatedClockPeriod>
</SummaryOfTimingAnalysis>
<SummaryOfOverallLatency>
<Best-caseLatency>2</Best-caseLatency>
<Average-caseLatency>2</Average-caseLatency>
<Worst-caseLatency>2</Worst-caseLatency>
<PipelineInitiationInterval>1</PipelineInitiationInterval>
<PipelineDepth>3</PipelineDepth>
<PipelineType>function</PipelineType>
</SummaryOfOverallLatency>
</PerformanceEstimates>
<AreaEstimates>
<Resources>
<FF>501</FF>
<LUT>303</LUT>
<BRAM_18K>0</BRAM_18K>
<DSP48E>0</DSP48E>
</Resources>
</AreaEstimates>
<InterfaceSummary>
<RtlPorts>
<name>ap_clk</name>
<Object>galapagos_to_tcp_int</Object>
<Type>return value</Type>
<Scope></Scope>
<IOProtocol>ap_ctrl_hs</IOProtocol>
<IOConfig></IOConfig>
<Dir>in</Dir>
<Bits>1</Bits>
<Attribute>control</Attribute>
</RtlPorts>
<RtlPorts>
<name>ap_rst</name>
<Object>galapagos_to_tcp_int</Object>
<Type>return value</Type>
<Scope></Scope>
<IOProtocol>ap_ctrl_hs</IOProtocol>
<IOConfig></IOConfig>
<Dir>in</Dir>
<Bits>1</Bits>
<Attribute>control</Attribute>
</RtlPorts>
<RtlPorts>
<name>ap_start</name>
<Object>galapagos_to_tcp_int</Object>
<Type>return value</Type>
<Scope></Scope>
<IOProtocol>ap_ctrl_hs</IOProtocol>
<IOConfig></IOConfig>
<Dir>in</Dir>
<Bits>1</Bits>
<Attribute>control</Attribute>
</RtlPorts>
<RtlPorts>
<name>start_full_n</name>
<Object>galapagos_to_tcp_int</Object>
<Type>return value</Type>
<Scope></Scope>
<IOProtocol>ap_ctrl_hs</IOProtocol>
<IOConfig></IOConfig>
<Dir>in</Dir>
<Bits>1</Bits>
<Attribute>unknown</Attribute>
</RtlPorts>
<RtlPorts>
<name>ap_done</name>
<Object>galapagos_to_tcp_int</Object>
<Type>return value</Type>
<Scope></Scope>
<IOProtocol>ap_ctrl_hs</IOProtocol>
<IOConfig></IOConfig>
<Dir>out</Dir>
<Bits>1</Bits>
<Attribute>control</Attribute>
</RtlPorts>
<RtlPorts>
<name>ap_continue</name>
<Object>galapagos_to_tcp_int</Object>
<Type>return value</Type>
<Scope></Scope>
<IOProtocol>ap_ctrl_hs</IOProtocol>
<IOConfig></IOConfig>
<Dir>in</Dir>
<Bits>1</Bits>
<Attribute>control</Attribute>
</RtlPorts>
<RtlPorts>
<name>ap_idle</name>
<Object>galapagos_to_tcp_int</Object>
<Type>return value</Type>
<Scope></Scope>
<IOProtocol>ap_ctrl_hs</IOProtocol>
<IOConfig></IOConfig>
<Dir>out</Dir>
<Bits>1</Bits>
<Attribute>control</Attribute>
</RtlPorts>
<RtlPorts>
<name>ap_ready</name>
<Object>galapagos_to_tcp_int</Object>
<Type>return value</Type>
<Scope></Scope>
<IOProtocol>ap_ctrl_hs</IOProtocol>
<IOConfig></IOConfig>
<Dir>out</Dir>
<Bits>1</Bits>
<Attribute>control</Attribute>
</RtlPorts>
<RtlPorts>
<name>start_out</name>
<Object>galapagos_to_tcp_int</Object>
<Type>return value</Type>
<Scope></Scope>
<IOProtocol>ap_ctrl_hs</IOProtocol>
<IOConfig></IOConfig>
<Dir>out</Dir>
<Bits>1</Bits>
<Attribute>unknown</Attribute>
</RtlPorts>
<RtlPorts>
<name>start_write</name>
<Object>galapagos_to_tcp_int</Object>
<Type>return value</Type>
<Scope></Scope>
<IOProtocol>ap_ctrl_hs</IOProtocol>
<IOConfig></IOConfig>
<Dir>out</Dir>
<Bits>1</Bits>
<Attribute>unknown</Attribute>
</RtlPorts>
<RtlPorts>
<name>rxGalapagosBridge_V_dout</name>
<Object>rxGalapagosBridge_V</Object>
<Type>pointer</Type>
<Scope></Scope>
<IOProtocol>ap_fifo</IOProtocol>
<IOConfig></IOConfig>
<Dir>in</Dir>
<Bits>73</Bits>
<Attribute>data</Attribute>
</RtlPorts>
<RtlPorts>
<name>rxGalapagosBridge_V_empty_n</name>
<Object>rxGalapagosBridge_V</Object>
<Type>pointer</Type>
<Scope></Scope>
<IOProtocol>ap_fifo</IOProtocol>
<IOConfig></IOConfig>
<Dir>in</Dir>
<Bits>1</Bits>
<Attribute>control</Attribute>
</RtlPorts>
<RtlPorts>
<name>rxGalapagosBridge_V_read</name>
<Object>rxGalapagosBridge_V</Object>
<Type>pointer</Type>
<Scope></Scope>
<IOProtocol>ap_fifo</IOProtocol>
<IOConfig></IOConfig>
<Dir>out</Dir>
<Bits>1</Bits>
<Attribute>control</Attribute>
</RtlPorts>
<RtlPorts>
<name>txStatus_V_V_dout</name>
<Object>txStatus_V_V</Object>
<Type>pointer</Type>
<Scope></Scope>
<IOProtocol>ap_fifo</IOProtocol>
<IOConfig></IOConfig>
<Dir>in</Dir>
<Bits>17</Bits>
<Attribute>data</Attribute>
</RtlPorts>
<RtlPorts>
<name>txStatus_V_V_empty_n</name>
<Object>txStatus_V_V</Object>
<Type>pointer</Type>
<Scope></Scope>
<IOProtocol>ap_fifo</IOProtocol>
<IOConfig></IOConfig>
<Dir>in</Dir>
<Bits>1</Bits>
<Attribute>control</Attribute>
</RtlPorts>
<RtlPorts>
<name>txStatus_V_V_read</name>
<Object>txStatus_V_V</Object>
<Type>pointer</Type>
<Scope></Scope>
<IOProtocol>ap_fifo</IOProtocol>
<IOConfig></IOConfig>
<Dir>out</Dir>
<Bits>1</Bits>
<Attribute>control</Attribute>
</RtlPorts>
<RtlPorts>
<name>sessionID_fifo_V_V_dout</name>
<Object>sessionID_fifo_V_V</Object>
<Type>pointer</Type>
<Scope>global</Scope>
<IOProtocol>ap_fifo</IOProtocol>
<IOConfig></IOConfig>
<Dir>in</Dir>
<Bits>16</Bits>
<Attribute>data</Attribute>
</RtlPorts>
<RtlPorts>
<name>sessionID_fifo_V_V_empty_n</name>
<Object>sessionID_fifo_V_V</Object>
<Type>pointer</Type>
<Scope>global</Scope>
<IOProtocol>ap_fifo</IOProtocol>
<IOConfig></IOConfig>
<Dir>in</Dir>
<Bits>1</Bits>
<Attribute>control</Attribute>
</RtlPorts>
<RtlPorts>
<name>sessionID_fifo_V_V_read</name>
<Object>sessionID_fifo_V_V</Object>
<Type>pointer</Type>
<Scope>global</Scope>
<IOProtocol>ap_fifo</IOProtocol>
<IOConfig></IOConfig>
<Dir>out</Dir>
<Bits>1</Bits>
<Attribute>control</Attribute>
</RtlPorts>
<RtlPorts>
<name>g2t_read_sid_V_V_dout</name>
<Object>g2t_read_sid_V_V</Object>
<Type>pointer</Type>
<Scope>global</Scope>
<IOProtocol>ap_fifo</IOProtocol>
<IOConfig></IOConfig>
<Dir>in</Dir>
<Bits>16</Bits>
<Attribute>data</Attribute>
</RtlPorts>
<RtlPorts>
<name>g2t_read_sid_V_V_empty_n</name>
<Object>g2t_read_sid_V_V</Object>
<Type>pointer</Type>
<Scope>global</Scope>
<IOProtocol>ap_fifo</IOProtocol>
<IOConfig></IOConfig>
<Dir>in</Dir>
<Bits>1</Bits>
<Attribute>control</Attribute>
</RtlPorts>
<RtlPorts>
<name>g2t_read_sid_V_V_read</name>
<Object>g2t_read_sid_V_V</Object>
<Type>pointer</Type>
<Scope>global</Scope>
<IOProtocol>ap_fifo</IOProtocol>
<IOConfig></IOConfig>
<Dir>out</Dir>
<Bits>1</Bits>
<Attribute>control</Attribute>
</RtlPorts>
<RtlPorts>
<name>g2t_write_sid_V_V_din</name>
<Object>g2t_write_sid_V_V</Object>
<Type>pointer</Type>
<Scope>global</Scope>
<IOProtocol>ap_fifo</IOProtocol>
<IOConfig></IOConfig>
<Dir>out</Dir>
<Bits>16</Bits>
<Attribute>data</Attribute>
</RtlPorts>
<RtlPorts>
<name>g2t_write_sid_V_V_full_n</name>
<Object>g2t_write_sid_V_V</Object>
<Type>pointer</Type>
<Scope>global</Scope>
<IOProtocol>ap_fifo</IOProtocol>
<IOConfig></IOConfig>
<Dir>in</Dir>
<Bits>1</Bits>
<Attribute>control</Attribute>
</RtlPorts>
<RtlPorts>
<name>g2t_write_sid_V_V_write</name>
<Object>g2t_write_sid_V_V</Object>
<Type>pointer</Type>
<Scope>global</Scope>
<IOProtocol>ap_fifo</IOProtocol>
<IOConfig></IOConfig>
<Dir>out</Dir>
<Bits>1</Bits>
<Attribute>control</Attribute>
</RtlPorts>
<RtlPorts>
<name>g2t_write_dest_V_V_din</name>
<Object>g2t_write_dest_V_V</Object>
<Type>pointer</Type>
<Scope>global</Scope>
<IOProtocol>ap_fifo</IOProtocol>
<IOConfig></IOConfig>
<Dir>out</Dir>
<Bits>8</Bits>
<Attribute>data</Attribute>
</RtlPorts>
<RtlPorts>
<name>g2t_write_dest_V_V_full_n</name>
<Object>g2t_write_dest_V_V</Object>
<Type>pointer</Type>
<Scope>global</Scope>
<IOProtocol>ap_fifo</IOProtocol>
<IOConfig></IOConfig>
<Dir>in</Dir>
<Bits>1</Bits>
<Attribute>control</Attribute>
</RtlPorts>
<RtlPorts>
<name>g2t_write_dest_V_V_write</name>
<Object>g2t_write_dest_V_V</Object>
<Type>pointer</Type>
<Scope>global</Scope>
<IOProtocol>ap_fifo</IOProtocol>
<IOConfig></IOConfig>
<Dir>out</Dir>
<Bits>1</Bits>
<Attribute>control</Attribute>
</RtlPorts>
<RtlPorts>
<name>g2t_read_dest_V_V_din</name>
<Object>g2t_read_dest_V_V</Object>
<Type>pointer</Type>
<Scope>global</Scope>
<IOProtocol>ap_fifo</IOProtocol>
<IOConfig></IOConfig>
<Dir>out</Dir>
<Bits>8</Bits>
<Attribute>data</Attribute>
</RtlPorts>
<RtlPorts>
<name>g2t_read_dest_V_V_full_n</name>
<Object>g2t_read_dest_V_V</Object>
<Type>pointer</Type>
<Scope>global</Scope>
<IOProtocol>ap_fifo</IOProtocol>
<IOConfig></IOConfig>
<Dir>in</Dir>
<Bits>1</Bits>
<Attribute>control</Attribute>
</RtlPorts>
<RtlPorts>
<name>g2t_read_dest_V_V_write</name>
<Object>g2t_read_dest_V_V</Object>
<Type>pointer</Type>
<Scope>global</Scope>
<IOProtocol>ap_fifo</IOProtocol>
<IOConfig></IOConfig>
<Dir>out</Dir>
<Bits>1</Bits>
<Attribute>control</Attribute>
</RtlPorts>
<RtlPorts>
<name>txData_V_din</name>
<Object>txData_V</Object>
<Type>pointer</Type>
<Scope></Scope>
<IOProtocol>ap_fifo</IOProtocol>
<IOConfig></IOConfig>
<Dir>out</Dir>
<Bits>73</Bits>
<Attribute>data</Attribute>
</RtlPorts>
<RtlPorts>
<name>txData_V_full_n</name>
<Object>txData_V</Object>
<Type>pointer</Type>
<Scope></Scope>
<IOProtocol>ap_fifo</IOProtocol>
<IOConfig></IOConfig>
<Dir>in</Dir>
<Bits>1</Bits>
<Attribute>control</Attribute>
</RtlPorts>
<RtlPorts>
<name>txData_V_write</name>
<Object>txData_V</Object>
<Type>pointer</Type>
<Scope></Scope>
<IOProtocol>ap_fifo</IOProtocol>
<IOConfig></IOConfig>
<Dir>out</Dir>
<Bits>1</Bits>
<Attribute>control</Attribute>
</RtlPorts>
<RtlPorts>
<name>txMetaData_V_din</name>
<Object>txMetaData_V</Object>
<Type>pointer</Type>
<Scope></Scope>
<IOProtocol>ap_fifo</IOProtocol>
<IOConfig></IOConfig>
<Dir>out</Dir>
<Bits>32</Bits>
<Attribute>data</Attribute>
</RtlPorts>
<RtlPorts>
<name>txMetaData_V_full_n</name>
<Object>txMetaData_V</Object>
<Type>pointer</Type>
<Scope></Scope>
<IOProtocol>ap_fifo</IOProtocol>
<IOConfig></IOConfig>
<Dir>in</Dir>
<Bits>1</Bits>
<Attribute>control</Attribute>
</RtlPorts>
<RtlPorts>
<name>txMetaData_V_write</name>
<Object>txMetaData_V</Object>
<Type>pointer</Type>
<Scope></Scope>
<IOProtocol>ap_fifo</IOProtocol>
<IOConfig></IOConfig>
<Dir>out</Dir>
<Bits>1</Bits>
<Attribute>control</Attribute>
</RtlPorts>
<RtlPorts>
<name>ip_fifo_V_V_din</name>
<Object>ip_fifo_V_V</Object>
<Type>pointer</Type>
<Scope>global</Scope>
<IOProtocol>ap_fifo</IOProtocol>
<IOConfig></IOConfig>
<Dir>out</Dir>
<Bits>32</Bits>
<Attribute>data</Attribute>
</RtlPorts>
<RtlPorts>
<name>ip_fifo_V_V_full_n</name>
<Object>ip_fifo_V_V</Object>
<Type>pointer</Type>
<Scope>global</Scope>
<IOProtocol>ap_fifo</IOProtocol>
<IOConfig></IOConfig>
<Dir>in</Dir>
<Bits>1</Bits>
<Attribute>control</Attribute>
</RtlPorts>
<RtlPorts>
<name>ip_fifo_V_V_write</name>
<Object>ip_fifo_V_V</Object>
<Type>pointer</Type>
<Scope>global</Scope>
<IOProtocol>ap_fifo</IOProtocol>
<IOConfig></IOConfig>
<Dir>out</Dir>
<Bits>1</Bits>
<Attribute>control</Attribute>
</RtlPorts>
<RtlPorts>
<name>state_out_V</name>
<Object>state_out_V</Object>
<Type>pointer</Type>
<Scope></Scope>
<IOProtocol>ap_vld</IOProtocol>
<IOConfig></IOConfig>
<Dir>out</Dir>
<Bits>4</Bits>
<Attribute>data</Attribute>
</RtlPorts>
<RtlPorts>
<name>state_out_V_ap_vld</name>
<Object>state_out_V</Object>
<Type>pointer</Type>
<Scope></Scope>
<IOProtocol>ap_vld</IOProtocol>
<IOConfig></IOConfig>
<Dir>out</Dir>
<Bits>1</Bits>
<Attribute>control</Attribute>
</RtlPorts>
<RtlPorts>
<name>header_out_V</name>
<Object>header_out_V</Object>
<Type>pointer</Type>
<Scope></Scope>
<IOProtocol>ap_vld</IOProtocol>
<IOConfig></IOConfig>
<Dir>out</Dir>
<Bits>64</Bits>
<Attribute>data</Attribute>
</RtlPorts>
<RtlPorts>
<name>header_out_V_ap_vld</name>
<Object>header_out_V</Object>
<Type>pointer</Type>
<Scope></Scope>
<IOProtocol>ap_vld</IOProtocol>
<IOConfig></IOConfig>
<Dir>out</Dir>
<Bits>1</Bits>
<Attribute>control</Attribute>
</RtlPorts>
<RtlPorts>
<name>size_out_V</name>
<Object>size_out_V</Object>
<Type>pointer</Type>
<Scope></Scope>
<IOProtocol>ap_vld</IOProtocol>
<IOConfig></IOConfig>
<Dir>out</Dir>
<Bits>16</Bits>
<Attribute>data</Attribute>
</RtlPorts>
<RtlPorts>
<name>size_out_V_ap_vld</name>
<Object>size_out_V</Object>
<Type>pointer</Type>
<Scope></Scope>
<IOProtocol>ap_vld</IOProtocol>
<IOConfig></IOConfig>
<Dir>out</Dir>
<Bits>1</Bits>
<Attribute>control</Attribute>
</RtlPorts>
<RtlPorts>
<name>sessionID_out_V</name>
<Object>sessionID_out_V</Object>
<Type>pointer</Type>
<Scope></Scope>
<IOProtocol>ap_vld</IOProtocol>
<IOConfig></IOConfig>
<Dir>out</Dir>
<Bits>16</Bits>
<Attribute>data</Attribute>
</RtlPorts>
<RtlPorts>
<name>sessionID_out_V_ap_vld</name>
<Object>sessionID_out_V</Object>
<Type>pointer</Type>
<Scope></Scope>
<IOProtocol>ap_vld</IOProtocol>
<IOConfig></IOConfig>
<Dir>out</Dir>
<Bits>1</Bits>
<Attribute>control</Attribute>
</RtlPorts>
<RtlPorts>
<name>ip_table_V_address0</name>
<Object>ip_table_V</Object>
<Type>array</Type>
<Scope>global</Scope>
<IOProtocol>ap_memory</IOProtocol>
<IOConfig></IOConfig>
<Dir>out</Dir>
<Bits>8</Bits>
<Attribute>address</Attribute>
</RtlPorts>
<RtlPorts>
<name>ip_table_V_ce0</name>
<Object>ip_table_V</Object>
<Type>array</Type>
<Scope>global</Scope>
<IOProtocol>ap_memory</IOProtocol>
<IOConfig></IOConfig>
<Dir>out</Dir>
<Bits>1</Bits>
<Attribute>control</Attribute>
</RtlPorts>
<RtlPorts>
<name>ip_table_V_q0</name>
<Object>ip_table_V</Object>
<Type>array</Type>
<Scope>global</Scope>
<IOProtocol>ap_memory</IOProtocol>
<IOConfig></IOConfig>
<Dir>in</Dir>
<Bits>32</Bits>
<Attribute>data</Attribute>
</RtlPorts>
</InterfaceSummary>
</Module>
<Module>
<Name>open_connections</Name>
<PerformanceEstimates>
<SummaryOfTimingAnalysis>
<TargetClockPeriod>4.00</TargetClockPeriod>
<ClockUncertainty>0.50</ClockUncertainty>
<TargetInitiationInterval>1</TargetInitiationInterval>
<EstimatedClockPeriod>1.75</EstimatedClockPeriod>
</SummaryOfTimingAnalysis>
<SummaryOfOverallLatency>
<Best-caseLatency>1</Best-caseLatency>
<Average-caseLatency>1</Average-caseLatency>
<Worst-caseLatency>1</Worst-caseLatency>
<PipelineInitiationInterval>1</PipelineInitiationInterval>
<PipelineDepth>2</PipelineDepth>
<PipelineType>function</PipelineType>
</SummaryOfOverallLatency>
</PerformanceEstimates>
<AreaEstimates>
<Resources>
<FF>55</FF>
<LUT>63</LUT>
<BRAM_18K>0</BRAM_18K>
<DSP48E>0</DSP48E>
</Resources>
</AreaEstimates>
<InterfaceSummary>
<RtlPorts>
<name>ap_clk</name>
<Object>open_connections</Object>
<Type>return value</Type>
<Scope></Scope>
<IOProtocol>ap_ctrl_hs</IOProtocol>
<IOConfig></IOConfig>
<Dir>in</Dir>
<Bits>1</Bits>
<Attribute>control</Attribute>
</RtlPorts>
<RtlPorts>
<name>ap_rst</name>
<Object>open_connections</Object>
<Type>return value</Type>
<Scope></Scope>
<IOProtocol>ap_ctrl_hs</IOProtocol>
<IOConfig></IOConfig>
<Dir>in</Dir>
<Bits>1</Bits>
<Attribute>control</Attribute>
</RtlPorts>
<RtlPorts>
<name>ap_start</name>
<Object>open_connections</Object>
<Type>return value</Type>
<Scope></Scope>
<IOProtocol>ap_ctrl_hs</IOProtocol>
<IOConfig></IOConfig>
<Dir>in</Dir>
<Bits>1</Bits>
<Attribute>control</Attribute>
</RtlPorts>
<RtlPorts>
<name>ap_done</name>
<Object>open_connections</Object>
<Type>return value</Type>
<Scope></Scope>
<IOProtocol>ap_ctrl_hs</IOProtocol>
<IOConfig></IOConfig>
<Dir>out</Dir>
<Bits>1</Bits>
<Attribute>control</Attribute>
</RtlPorts>
<RtlPorts>
<name>ap_continue</name>
<Object>open_connections</Object>
<Type>return value</Type>
<Scope></Scope>
<IOProtocol>ap_ctrl_hs</IOProtocol>
<IOConfig></IOConfig>
<Dir>in</Dir>
<Bits>1</Bits>
<Attribute>control</Attribute>
</RtlPorts>
<RtlPorts>
<name>ap_idle</name>
<Object>open_connections</Object>
<Type>return value</Type>
<Scope></Scope>
<IOProtocol>ap_ctrl_hs</IOProtocol>
<IOConfig></IOConfig>
<Dir>out</Dir>
<Bits>1</Bits>
<Attribute>control</Attribute>
</RtlPorts>
<RtlPorts>
<name>ap_ready</name>
<Object>open_connections</Object>
<Type>return value</Type>
<Scope></Scope>
<IOProtocol>ap_ctrl_hs</IOProtocol>
<IOConfig></IOConfig>
<Dir>out</Dir>
<Bits>1</Bits>
<Attribute>control</Attribute>
</RtlPorts>
<RtlPorts>
<name>ip_fifo_V_V_dout</name>
<Object>ip_fifo_V_V</Object>
<Type>pointer</Type>
<Scope>global</Scope>
<IOProtocol>ap_fifo</IOProtocol>
<IOConfig></IOConfig>
<Dir>in</Dir>
<Bits>32</Bits>
<Attribute>data</Attribute>
</RtlPorts>
<RtlPorts>
<name>ip_fifo_V_V_empty_n</name>
<Object>ip_fifo_V_V</Object>
<Type>pointer</Type>
<Scope>global</Scope>
<IOProtocol>ap_fifo</IOProtocol>
<IOConfig></IOConfig>
<Dir>in</Dir>
<Bits>1</Bits>
<Attribute>control</Attribute>
</RtlPorts>
<RtlPorts>
<name>ip_fifo_V_V_read</name>
<Object>ip_fifo_V_V</Object>
<Type>pointer</Type>
<Scope>global</Scope>
<IOProtocol>ap_fifo</IOProtocol>
<IOConfig></IOConfig>
<Dir>out</Dir>
<Bits>1</Bits>
<Attribute>control</Attribute>
</RtlPorts>
<RtlPorts>
<name>openConStatus_V_dout</name>
<Object>openConStatus_V</Object>
<Type>pointer</Type>
<Scope></Scope>
<IOProtocol>ap_fifo</IOProtocol>
<IOConfig></IOConfig>
<Dir>in</Dir>
<Bits>17</Bits>
<Attribute>data</Attribute>
</RtlPorts>
<RtlPorts>
<name>openConStatus_V_empty_n</name>
<Object>openConStatus_V</Object>
<Type>pointer</Type>
<Scope></Scope>
<IOProtocol>ap_fifo</IOProtocol>
<IOConfig></IOConfig>
<Dir>in</Dir>
<Bits>1</Bits>
<Attribute>control</Attribute>
</RtlPorts>
<RtlPorts>
<name>openConStatus_V_read</name>
<Object>openConStatus_V</Object>
<Type>pointer</Type>
<Scope></Scope>
<IOProtocol>ap_fifo</IOProtocol>
<IOConfig></IOConfig>
<Dir>out</Dir>
<Bits>1</Bits>
<Attribute>control</Attribute>
</RtlPorts>
<RtlPorts>
<name>openConnection_V_din</name>
<Object>openConnection_V</Object>
<Type>pointer</Type>
<Scope></Scope>
<IOProtocol>ap_fifo</IOProtocol>
<IOConfig></IOConfig>
<Dir>out</Dir>
<Bits>48</Bits>
<Attribute>data</Attribute>
</RtlPorts>
<RtlPorts>
<name>openConnection_V_full_n</name>
<Object>openConnection_V</Object>
<Type>pointer</Type>
<Scope></Scope>
<IOProtocol>ap_fifo</IOProtocol>
<IOConfig></IOConfig>
<Dir>in</Dir>
<Bits>1</Bits>
<Attribute>control</Attribute>
</RtlPorts>
<RtlPorts>
<name>openConnection_V_write</name>
<Object>openConnection_V</Object>
<Type>pointer</Type>
<Scope></Scope>
<IOProtocol>ap_fifo</IOProtocol>
<IOConfig></IOConfig>
<Dir>out</Dir>
<Bits>1</Bits>
<Attribute>control</Attribute>
</RtlPorts>
<RtlPorts>
<name>sessionID_fifo_V_V_din</name>
<Object>sessionID_fifo_V_V</Object>
<Type>pointer</Type>
<Scope>global</Scope>
<IOProtocol>ap_fifo</IOProtocol>
<IOConfig></IOConfig>
<Dir>out</Dir>
<Bits>16</Bits>
<Attribute>data</Attribute>
</RtlPorts>
<RtlPorts>
<name>sessionID_fifo_V_V_full_n</name>
<Object>sessionID_fifo_V_V</Object>
<Type>pointer</Type>
<Scope>global</Scope>
<IOProtocol>ap_fifo</IOProtocol>
<IOConfig></IOConfig>
<Dir>in</Dir>
<Bits>1</Bits>
<Attribute>control</Attribute>
</RtlPorts>
<RtlPorts>
<name>sessionID_fifo_V_V_write</name>
<Object>sessionID_fifo_V_V</Object>
<Type>pointer</Type>
<Scope>global</Scope>
<IOProtocol>ap_fifo</IOProtocol>
<IOConfig></IOConfig>
<Dir>out</Dir>
<Bits>1</Bits>
<Attribute>control</Attribute>
</RtlPorts>
</InterfaceSummary>
</Module>
<Module>
<Name>open_port</Name>
<PerformanceEstimates>
<SummaryOfTimingAnalysis>
<TargetClockPeriod>4.00</TargetClockPeriod>
<ClockUncertainty>0.50</ClockUncertainty>
<TargetInitiationInterval>1</TargetInitiationInterval>
<EstimatedClockPeriod>1.10</EstimatedClockPeriod>
</SummaryOfTimingAnalysis>
<SummaryOfOverallLatency>
<Best-caseLatency>1</Best-caseLatency>
<Average-caseLatency>1</Average-caseLatency>
<Worst-caseLatency>1</Worst-caseLatency>
<PipelineInitiationInterval>1</PipelineInitiationInterval>
<PipelineDepth>2</PipelineDepth>
<PipelineType>function</PipelineType>
</SummaryOfOverallLatency>
</PerformanceEstimates>
<AreaEstimates>
<Resources>
<FF>40</FF>
<LUT>74</LUT>
<BRAM_18K>0</BRAM_18K>
<DSP48E>0</DSP48E>
</Resources>
</AreaEstimates>
<InterfaceSummary>
<RtlPorts>
<name>ap_clk</name>
<Object>open_port</Object>
<Type>return value</Type>
<Scope></Scope>
<IOProtocol>ap_ctrl_hs</IOProtocol>
<IOConfig></IOConfig>
<Dir>in</Dir>
<Bits>1</Bits>
<Attribute>control</Attribute>
</RtlPorts>
<RtlPorts>
<name>ap_rst</name>
<Object>open_port</Object>
<Type>return value</Type>
<Scope></Scope>
<IOProtocol>ap_ctrl_hs</IOProtocol>
<IOConfig></IOConfig>
<Dir>in</Dir>
<Bits>1</Bits>
<Attribute>control</Attribute>
</RtlPorts>
<RtlPorts>
<name>ap_start</name>
<Object>open_port</Object>
<Type>return value</Type>
<Scope></Scope>
<IOProtocol>ap_ctrl_hs</IOProtocol>
<IOConfig></IOConfig>
<Dir>in</Dir>
<Bits>1</Bits>
<Attribute>control</Attribute>
</RtlPorts>
<RtlPorts>
<name>ap_done</name>
<Object>open_port</Object>
<Type>return value</Type>
<Scope></Scope>
<IOProtocol>ap_ctrl_hs</IOProtocol>
<IOConfig></IOConfig>
<Dir>out</Dir>
<Bits>1</Bits>
<Attribute>control</Attribute>
</RtlPorts>
<RtlPorts>
<name>ap_continue</name>
<Object>open_port</Object>
<Type>return value</Type>
<Scope></Scope>
<IOProtocol>ap_ctrl_hs</IOProtocol>
<IOConfig></IOConfig>
<Dir>in</Dir>
<Bits>1</Bits>
<Attribute>control</Attribute>
</RtlPorts>
<RtlPorts>
<name>ap_idle</name>
<Object>open_port</Object>
<Type>return value</Type>
<Scope></Scope>
<IOProtocol>ap_ctrl_hs</IOProtocol>
<IOConfig></IOConfig>
<Dir>out</Dir>
<Bits>1</Bits>
<Attribute>control</Attribute>
</RtlPorts>
<RtlPorts>
<name>ap_ready</name>
<Object>open_port</Object>
<Type>return value</Type>
<Scope></Scope>
<IOProtocol>ap_ctrl_hs</IOProtocol>
<IOConfig></IOConfig>
<Dir>out</Dir>
<Bits>1</Bits>
<Attribute>control</Attribute>
</RtlPorts>
<RtlPorts>
<name>listenPortStatus_V_dout</name>
<Object>listenPortStatus_V</Object>
<Type>pointer</Type>
<Scope></Scope>
<IOProtocol>ap_fifo</IOProtocol>
<IOConfig></IOConfig>
<Dir>in</Dir>
<Bits>1</Bits>
<Attribute>data</Attribute>
</RtlPorts>
<RtlPorts>
<name>listenPortStatus_V_empty_n</name>
<Object>listenPortStatus_V</Object>
<Type>pointer</Type>
<Scope></Scope>
<IOProtocol>ap_fifo</IOProtocol>
<IOConfig></IOConfig>
<Dir>in</Dir>
<Bits>1</Bits>
<Attribute>control</Attribute>
</RtlPorts>
<RtlPorts>
<name>listenPortStatus_V_read</name>
<Object>listenPortStatus_V</Object>
<Type>pointer</Type>
<Scope></Scope>
<IOProtocol>ap_fifo</IOProtocol>
<IOConfig></IOConfig>
<Dir>out</Dir>
<Bits>1</Bits>
<Attribute>control</Attribute>
</RtlPorts>
<RtlPorts>
<name>notifications_V_dout</name>
<Object>notifications_V</Object>
<Type>pointer</Type>
<Scope></Scope>
<IOProtocol>ap_fifo</IOProtocol>
<IOConfig></IOConfig>
<Dir>in</Dir>
<Bits>81</Bits>
<Attribute>data</Attribute>
</RtlPorts>
<RtlPorts>
<name>notifications_V_empty_n</name>
<Object>notifications_V</Object>
<Type>pointer</Type>
<Scope></Scope>
<IOProtocol>ap_fifo</IOProtocol>
<IOConfig></IOConfig>
<Dir>in</Dir>
<Bits>1</Bits>
<Attribute>control</Attribute>
</RtlPorts>
<RtlPorts>
<name>notifications_V_read</name>
<Object>notifications_V</Object>
<Type>pointer</Type>
<Scope></Scope>
<IOProtocol>ap_fifo</IOProtocol>
<IOConfig></IOConfig>
<Dir>out</Dir>
<Bits>1</Bits>
<Attribute>control</Attribute>
</RtlPorts>
<RtlPorts>
<name>listenPort_V_V_din</name>
<Object>listenPort_V_V</Object>
<Type>pointer</Type>
<Scope></Scope>
<IOProtocol>ap_fifo</IOProtocol>
<IOConfig></IOConfig>
<Dir>out</Dir>
<Bits>16</Bits>
<Attribute>data</Attribute>
</RtlPorts>
<RtlPorts>
<name>listenPort_V_V_full_n</name>
<Object>listenPort_V_V</Object>
<Type>pointer</Type>
<Scope></Scope>
<IOProtocol>ap_fifo</IOProtocol>
<IOConfig></IOConfig>
<Dir>in</Dir>
<Bits>1</Bits>
<Attribute>control</Attribute>
</RtlPorts>
<RtlPorts>
<name>listenPort_V_V_write</name>
<Object>listenPort_V_V</Object>
<Type>pointer</Type>
<Scope></Scope>
<IOProtocol>ap_fifo</IOProtocol>
<IOConfig></IOConfig>
<Dir>out</Dir>
<Bits>1</Bits>
<Attribute>control</Attribute>
</RtlPorts>
<RtlPorts>
<name>readRequest_V_din</name>
<Object>readRequest_V</Object>
<Type>pointer</Type>
<Scope></Scope>
<IOProtocol>ap_fifo</IOProtocol>
<IOConfig></IOConfig>
<Dir>out</Dir>
<Bits>32</Bits>
<Attribute>data</Attribute>
</RtlPorts>
<RtlPorts>
<name>readRequest_V_full_n</name>
<Object>readRequest_V</Object>
<Type>pointer</Type>
<Scope></Scope>
<IOProtocol>ap_fifo</IOProtocol>
<IOConfig></IOConfig>
<Dir>in</Dir>
<Bits>1</Bits>
<Attribute>control</Attribute>
</RtlPorts>
<RtlPorts>
<name>readRequest_V_write</name>
<Object>readRequest_V</Object>
<Type>pointer</Type>
<Scope></Scope>
<IOProtocol>ap_fifo</IOProtocol>
<IOConfig></IOConfig>
<Dir>out</Dir>
<Bits>1</Bits>
<Attribute>control</Attribute>
</RtlPorts>
</InterfaceSummary>
</Module>
<Module>
<Name>tcp_to_galapagos_int</Name>
<PerformanceEstimates>
<SummaryOfTimingAnalysis>
<TargetClockPeriod>4.00</TargetClockPeriod>
<ClockUncertainty>0.50</ClockUncertainty>
<TargetInitiationInterval>1</TargetInitiationInterval>
<EstimatedClockPeriod>4.21</EstimatedClockPeriod>
</SummaryOfTimingAnalysis>
<SummaryOfOverallLatency>
<Best-caseLatency>1</Best-caseLatency>
<Average-caseLatency>1</Average-caseLatency>
<Worst-caseLatency>1</Worst-caseLatency>
<PipelineInitiationInterval>1</PipelineInitiationInterval>
<PipelineDepth>2</PipelineDepth>
<PipelineType>function</PipelineType>
</SummaryOfOverallLatency>
</PerformanceEstimates>
<AreaEstimates>
<Resources>
<FF>189</FF>
<LUT>159</LUT>
<BRAM_18K>0</BRAM_18K>
<DSP48E>0</DSP48E>
</Resources>
</AreaEstimates>
<InterfaceSummary>
<RtlPorts>
<name>ap_clk</name>
<Object>tcp_to_galapagos_int</Object>
<Type>return value</Type>
<Scope></Scope>
<IOProtocol>ap_ctrl_hs</IOProtocol>
<IOConfig></IOConfig>
<Dir>in</Dir>
<Bits>1</Bits>
<Attribute>control</Attribute>
</RtlPorts>
<RtlPorts>
<name>ap_rst</name>
<Object>tcp_to_galapagos_int</Object>
<Type>return value</Type>
<Scope></Scope>
<IOProtocol>ap_ctrl_hs</IOProtocol>
<IOConfig></IOConfig>
<Dir>in</Dir>
<Bits>1</Bits>
<Attribute>control</Attribute>
</RtlPorts>
<RtlPorts>
<name>ap_start</name>
<Object>tcp_to_galapagos_int</Object>
<Type>return value</Type>
<Scope></Scope>
<IOProtocol>ap_ctrl_hs</IOProtocol>
<IOConfig></IOConfig>
<Dir>in</Dir>
<Bits>1</Bits>
<Attribute>control</Attribute>
</RtlPorts>
<RtlPorts>
<name>ap_done</name>
<Object>tcp_to_galapagos_int</Object>
<Type>return value</Type>
<Scope></Scope>
<IOProtocol>ap_ctrl_hs</IOProtocol>
<IOConfig></IOConfig>
<Dir>out</Dir>
<Bits>1</Bits>
<Attribute>control</Attribute>
</RtlPorts>
<RtlPorts>
<name>ap_continue</name>
<Object>tcp_to_galapagos_int</Object>
<Type>return value</Type>
<Scope></Scope>
<IOProtocol>ap_ctrl_hs</IOProtocol>
<IOConfig></IOConfig>
<Dir>in</Dir>
<Bits>1</Bits>
<Attribute>control</Attribute>
</RtlPorts>
<RtlPorts>
<name>ap_idle</name>
<Object>tcp_to_galapagos_int</Object>
<Type>return value</Type>
<Scope></Scope>
<IOProtocol>ap_ctrl_hs</IOProtocol>
<IOConfig></IOConfig>
<Dir>out</Dir>
<Bits>1</Bits>
<Attribute>control</Attribute>
</RtlPorts>
<RtlPorts>
<name>ap_ready</name>
<Object>tcp_to_galapagos_int</Object>
<Type>return value</Type>
<Scope></Scope>
<IOProtocol>ap_ctrl_hs</IOProtocol>
<IOConfig></IOConfig>
<Dir>out</Dir>
<Bits>1</Bits>
<Attribute>control</Attribute>
</RtlPorts>
<RtlPorts>
<name>rxData_V_dout</name>
<Object>rxData_V</Object>
<Type>pointer</Type>
<Scope></Scope>
<IOProtocol>ap_fifo</IOProtocol>
<IOConfig></IOConfig>
<Dir>in</Dir>
<Bits>73</Bits>
<Attribute>data</Attribute>
</RtlPorts>
<RtlPorts>
<name>rxData_V_empty_n</name>
<Object>rxData_V</Object>
<Type>pointer</Type>
<Scope></Scope>
<IOProtocol>ap_fifo</IOProtocol>
<IOConfig></IOConfig>
<Dir>in</Dir>
<Bits>1</Bits>
<Attribute>control</Attribute>
</RtlPorts>
<RtlPorts>
<name>rxData_V_read</name>
<Object>rxData_V</Object>
<Type>pointer</Type>
<Scope></Scope>
<IOProtocol>ap_fifo</IOProtocol>
<IOConfig></IOConfig>
<Dir>out</Dir>
<Bits>1</Bits>
<Attribute>control</Attribute>
</RtlPorts>
<RtlPorts>
<name>t2g_read_sid_V_V_dout</name>
<Object>t2g_read_sid_V_V</Object>
<Type>pointer</Type>
<Scope>global</Scope>
<IOProtocol>ap_fifo</IOProtocol>
<IOConfig></IOConfig>
<Dir>in</Dir>
<Bits>16</Bits>
<Attribute>data</Attribute>
</RtlPorts>
<RtlPorts>
<name>t2g_read_sid_V_V_empty_n</name>
<Object>t2g_read_sid_V_V</Object>
<Type>pointer</Type>
<Scope>global</Scope>
<IOProtocol>ap_fifo</IOProtocol>
<IOConfig></IOConfig>
<Dir>in</Dir>
<Bits>1</Bits>
<Attribute>control</Attribute>
</RtlPorts>
<RtlPorts>
<name>t2g_read_sid_V_V_read</name>
<Object>t2g_read_sid_V_V</Object>
<Type>pointer</Type>
<Scope>global</Scope>
<IOProtocol>ap_fifo</IOProtocol>
<IOConfig></IOConfig>
<Dir>out</Dir>
<Bits>1</Bits>
<Attribute>control</Attribute>
</RtlPorts>
<RtlPorts>
<name>rxMetaData_V_V_dout</name>
<Object>rxMetaData_V_V</Object>
<Type>pointer</Type>
<Scope></Scope>
<IOProtocol>ap_fifo</IOProtocol>
<IOConfig></IOConfig>
<Dir>in</Dir>
<Bits>16</Bits>
<Attribute>data</Attribute>
</RtlPorts>
<RtlPorts>
<name>rxMetaData_V_V_empty_n</name>
<Object>rxMetaData_V_V</Object>
<Type>pointer</Type>
<Scope></Scope>
<IOProtocol>ap_fifo</IOProtocol>
<IOConfig></IOConfig>
<Dir>in</Dir>
<Bits>1</Bits>
<Attribute>control</Attribute>
</RtlPorts>
<RtlPorts>
<name>rxMetaData_V_V_read</name>
<Object>rxMetaData_V_V</Object>
<Type>pointer</Type>
<Scope></Scope>
<IOProtocol>ap_fifo</IOProtocol>
<IOConfig></IOConfig>
<Dir>out</Dir>
<Bits>1</Bits>
<Attribute>control</Attribute>
</RtlPorts>
<RtlPorts>
<name>txGalapagosBridge_V_din</name>
<Object>txGalapagosBridge_V</Object>
<Type>pointer</Type>
<Scope></Scope>
<IOProtocol>ap_fifo</IOProtocol>
<IOConfig></IOConfig>
<Dir>out</Dir>
<Bits>73</Bits>
<Attribute>data</Attribute>
</RtlPorts>
<RtlPorts>
<name>txGalapagosBridge_V_full_n</name>
<Object>txGalapagosBridge_V</Object>
<Type>pointer</Type>
<Scope></Scope>
<IOProtocol>ap_fifo</IOProtocol>
<IOConfig></IOConfig>
<Dir>in</Dir>
<Bits>1</Bits>
<Attribute>control</Attribute>
</RtlPorts>
<RtlPorts>
<name>txGalapagosBridge_V_write</name>
<Object>txGalapagosBridge_V</Object>
<Type>pointer</Type>
<Scope></Scope>
<IOProtocol>ap_fifo</IOProtocol>
<IOConfig></IOConfig>
<Dir>out</Dir>
<Bits>1</Bits>
<Attribute>control</Attribute>
</RtlPorts>
<RtlPorts>
<name>t2g_write_dest_V_V_din</name>
<Object>t2g_write_dest_V_V</Object>
<Type>pointer</Type>
<Scope>global</Scope>
<IOProtocol>ap_fifo</IOProtocol>
<IOConfig></IOConfig>
<Dir>out</Dir>
<Bits>8</Bits>
<Attribute>data</Attribute>
</RtlPorts>
<RtlPorts>
<name>t2g_write_dest_V_V_full_n</name>
<Object>t2g_write_dest_V_V</Object>
<Type>pointer</Type>
<Scope>global</Scope>
<IOProtocol>ap_fifo</IOProtocol>
<IOConfig></IOConfig>
<Dir>in</Dir>
<Bits>1</Bits>
<Attribute>control</Attribute>
</RtlPorts>
<RtlPorts>
<name>t2g_write_dest_V_V_write</name>
<Object>t2g_write_dest_V_V</Object>
<Type>pointer</Type>
<Scope>global</Scope>
<IOProtocol>ap_fifo</IOProtocol>
<IOConfig></IOConfig>
<Dir>out</Dir>
<Bits>1</Bits>
<Attribute>control</Attribute>
</RtlPorts>
<RtlPorts>
<name>t2g_write_sid_V_V_din</name>
<Object>t2g_write_sid_V_V</Object>
<Type>pointer</Type>
<Scope>global</Scope>
<IOProtocol>ap_fifo</IOProtocol>
<IOConfig></IOConfig>
<Dir>out</Dir>
<Bits>16</Bits>
<Attribute>data</Attribute>
</RtlPorts>
<RtlPorts>
<name>t2g_write_sid_V_V_full_n</name>
<Object>t2g_write_sid_V_V</Object>
<Type>pointer</Type>
<Scope>global</Scope>
<IOProtocol>ap_fifo</IOProtocol>
<IOConfig></IOConfig>
<Dir>in</Dir>
<Bits>1</Bits>
<Attribute>control</Attribute>
</RtlPorts>
<RtlPorts>
<name>t2g_write_sid_V_V_write</name>
<Object>t2g_write_sid_V_V</Object>
<Type>pointer</Type>
<Scope>global</Scope>
<IOProtocol>ap_fifo</IOProtocol>
<IOConfig></IOConfig>
<Dir>out</Dir>
<Bits>1</Bits>
<Attribute>control</Attribute>
</RtlPorts>
<RtlPorts>
<name>t2g_read_dest_V_V_din</name>
<Object>t2g_read_dest_V_V</Object>
<Type>pointer</Type>
<Scope>global</Scope>
<IOProtocol>ap_fifo</IOProtocol>
<IOConfig></IOConfig>
<Dir>out</Dir>
<Bits>8</Bits>
<Attribute>data</Attribute>
</RtlPorts>
<RtlPorts>
<name>t2g_read_dest_V_V_full_n</name>
<Object>t2g_read_dest_V_V</Object>
<Type>pointer</Type>
<Scope>global</Scope>
<IOProtocol>ap_fifo</IOProtocol>
<IOConfig></IOConfig>
<Dir>in</Dir>
<Bits>1</Bits>
<Attribute>control</Attribute>
</RtlPorts>
<RtlPorts>
<name>t2g_read_dest_V_V_write</name>
<Object>t2g_read_dest_V_V</Object>
<Type>pointer</Type>
<Scope>global</Scope>
<IOProtocol>ap_fifo</IOProtocol>
<IOConfig></IOConfig>
<Dir>out</Dir>
<Bits>1</Bits>
<Attribute>control</Attribute>
</RtlPorts>
</InterfaceSummary>
</Module>
<Module>
<Name>sessionID_table_stea</Name>
<PerformanceEstimates>
<SummaryOfTimingAnalysis>
<TargetClockPeriod>4.00</TargetClockPeriod>
<ClockUncertainty>0.50</ClockUncertainty>
<TargetInitiationInterval>1</TargetInitiationInterval>
<EstimatedClockPeriod>1.77</EstimatedClockPeriod>
</SummaryOfTimingAnalysis>
<SummaryOfOverallLatency>
<Best-caseLatency>6</Best-caseLatency>
<Average-caseLatency>6</Average-caseLatency>
<Worst-caseLatency>6</Worst-caseLatency>
<PipelineInitiationInterval>1</PipelineInitiationInterval>
<PipelineDepth>7</PipelineDepth>
<PipelineType>function</PipelineType>
</SummaryOfOverallLatency>
</PerformanceEstimates>
<AreaEstimates>
<Resources>
<BRAM_18K>1</BRAM_18K>
<FF>566</FF>
<LUT>375</LUT>
<DSP48E>0</DSP48E>
</Resources>
</AreaEstimates>
<InterfaceSummary>
<RtlPorts>
<name>ap_clk</name>
<Object>sessionID_table_stea</Object>
<Type>return value</Type>
<Scope></Scope>
<IOProtocol>ap_ctrl_hs</IOProtocol>
<IOConfig></IOConfig>
<Dir>in</Dir>
<Bits>1</Bits>
<Attribute>control</Attribute>
</RtlPorts>
<RtlPorts>
<name>ap_rst</name>
<Object>sessionID_table_stea</Object>
<Type>return value</Type>
<Scope></Scope>
<IOProtocol>ap_ctrl_hs</IOProtocol>
<IOConfig></IOConfig>
<Dir>in</Dir>
<Bits>1</Bits>
<Attribute>control</Attribute>
</RtlPorts>
<RtlPorts>
<name>ap_start</name>
<Object>sessionID_table_stea</Object>
<Type>return value</Type>
<Scope></Scope>
<IOProtocol>ap_ctrl_hs</IOProtocol>
<IOConfig></IOConfig>
<Dir>in</Dir>
<Bits>1</Bits>
<Attribute>control</Attribute>
</RtlPorts>
<RtlPorts>
<name>ap_done</name>
<Object>sessionID_table_stea</Object>
<Type>return value</Type>
<Scope></Scope>
<IOProtocol>ap_ctrl_hs</IOProtocol>
<IOConfig></IOConfig>
<Dir>out</Dir>
<Bits>1</Bits>
<Attribute>control</Attribute>
</RtlPorts>
<RtlPorts>
<name>ap_continue</name>
<Object>sessionID_table_stea</Object>
<Type>return value</Type>
<Scope></Scope>
<IOProtocol>ap_ctrl_hs</IOProtocol>
<IOConfig></IOConfig>
<Dir>in</Dir>
<Bits>1</Bits>
<Attribute>control</Attribute>
</RtlPorts>
<RtlPorts>
<name>ap_idle</name>
<Object>sessionID_table_stea</Object>
<Type>return value</Type>
<Scope></Scope>
<IOProtocol>ap_ctrl_hs</IOProtocol>
<IOConfig></IOConfig>
<Dir>out</Dir>
<Bits>1</Bits>
<Attribute>control</Attribute>
</RtlPorts>
<RtlPorts>
<name>ap_ready</name>
<Object>sessionID_table_stea</Object>
<Type>return value</Type>
<Scope></Scope>
<IOProtocol>ap_ctrl_hs</IOProtocol>
<IOConfig></IOConfig>
<Dir>out</Dir>
<Bits>1</Bits>
<Attribute>control</Attribute>
</RtlPorts>
<RtlPorts>
<name>t2g_read_dest_V_V_dout</name>
<Object>t2g_read_dest_V_V</Object>
<Type>pointer</Type>
<Scope>global</Scope>
<IOProtocol>ap_fifo</IOProtocol>
<IOConfig></IOConfig>
<Dir>in</Dir>
<Bits>8</Bits>
<Attribute>data</Attribute>
</RtlPorts>
<RtlPorts>
<name>t2g_read_dest_V_V_empty_n</name>
<Object>t2g_read_dest_V_V</Object>
<Type>pointer</Type>
<Scope>global</Scope>
<IOProtocol>ap_fifo</IOProtocol>
<IOConfig></IOConfig>
<Dir>in</Dir>
<Bits>1</Bits>
<Attribute>control</Attribute>
</RtlPorts>
<RtlPorts>
<name>t2g_read_dest_V_V_read</name>
<Object>t2g_read_dest_V_V</Object>
<Type>pointer</Type>
<Scope>global</Scope>
<IOProtocol>ap_fifo</IOProtocol>
<IOConfig></IOConfig>
<Dir>out</Dir>
<Bits>1</Bits>
<Attribute>control</Attribute>
</RtlPorts>
<RtlPorts>
<name>t2g_write_dest_V_V_dout</name>
<Object>t2g_write_dest_V_V</Object>
<Type>pointer</Type>
<Scope>global</Scope>
<IOProtocol>ap_fifo</IOProtocol>
<IOConfig></IOConfig>
<Dir>in</Dir>
<Bits>8</Bits>
<Attribute>data</Attribute>
</RtlPorts>
<RtlPorts>
<name>t2g_write_dest_V_V_empty_n</name>
<Object>t2g_write_dest_V_V</Object>
<Type>pointer</Type>
<Scope>global</Scope>
<IOProtocol>ap_fifo</IOProtocol>
<IOConfig></IOConfig>
<Dir>in</Dir>
<Bits>1</Bits>
<Attribute>control</Attribute>
</RtlPorts>
<RtlPorts>
<name>t2g_write_dest_V_V_read</name>
<Object>t2g_write_dest_V_V</Object>
<Type>pointer</Type>
<Scope>global</Scope>
<IOProtocol>ap_fifo</IOProtocol>
<IOConfig></IOConfig>
<Dir>out</Dir>
<Bits>1</Bits>
<Attribute>control</Attribute>
</RtlPorts>
<RtlPorts>
<name>t2g_write_sid_V_V_dout</name>
<Object>t2g_write_sid_V_V</Object>
<Type>pointer</Type>
<Scope>global</Scope>
<IOProtocol>ap_fifo</IOProtocol>
<IOConfig></IOConfig>
<Dir>in</Dir>
<Bits>16</Bits>
<Attribute>data</Attribute>
</RtlPorts>
<RtlPorts>
<name>t2g_write_sid_V_V_empty_n</name>
<Object>t2g_write_sid_V_V</Object>
<Type>pointer</Type>
<Scope>global</Scope>
<IOProtocol>ap_fifo</IOProtocol>
<IOConfig></IOConfig>
<Dir>in</Dir>
<Bits>1</Bits>
<Attribute>control</Attribute>
</RtlPorts>
<RtlPorts>
<name>t2g_write_sid_V_V_read</name>
<Object>t2g_write_sid_V_V</Object>
<Type>pointer</Type>
<Scope>global</Scope>
<IOProtocol>ap_fifo</IOProtocol>
<IOConfig></IOConfig>
<Dir>out</Dir>
<Bits>1</Bits>
<Attribute>control</Attribute>
</RtlPorts>
<RtlPorts>
<name>g2t_read_dest_V_V_dout</name>
<Object>g2t_read_dest_V_V</Object>
<Type>pointer</Type>
<Scope>global</Scope>
<IOProtocol>ap_fifo</IOProtocol>
<IOConfig></IOConfig>
<Dir>in</Dir>
<Bits>8</Bits>
<Attribute>data</Attribute>
</RtlPorts>
<RtlPorts>
<name>g2t_read_dest_V_V_empty_n</name>
<Object>g2t_read_dest_V_V</Object>
<Type>pointer</Type>
<Scope>global</Scope>
<IOProtocol>ap_fifo</IOProtocol>
<IOConfig></IOConfig>
<Dir>in</Dir>
<Bits>1</Bits>
<Attribute>control</Attribute>
</RtlPorts>
<RtlPorts>
<name>g2t_read_dest_V_V_read</name>
<Object>g2t_read_dest_V_V</Object>
<Type>pointer</Type>
<Scope>global</Scope>
<IOProtocol>ap_fifo</IOProtocol>
<IOConfig></IOConfig>
<Dir>out</Dir>
<Bits>1</Bits>
<Attribute>control</Attribute>
</RtlPorts>
<RtlPorts>
<name>g2t_write_dest_V_V_dout</name>
<Object>g2t_write_dest_V_V</Object>
<Type>pointer</Type>
<Scope>global</Scope>
<IOProtocol>ap_fifo</IOProtocol>
<IOConfig></IOConfig>
<Dir>in</Dir>
<Bits>8</Bits>
<Attribute>data</Attribute>
</RtlPorts>
<RtlPorts>
<name>g2t_write_dest_V_V_empty_n</name>
<Object>g2t_write_dest_V_V</Object>
<Type>pointer</Type>
<Scope>global</Scope>
<IOProtocol>ap_fifo</IOProtocol>
<IOConfig></IOConfig>
<Dir>in</Dir>
<Bits>1</Bits>
<Attribute>control</Attribute>
</RtlPorts>
<RtlPorts>
<name>g2t_write_dest_V_V_read</name>
<Object>g2t_write_dest_V_V</Object>
<Type>pointer</Type>
<Scope>global</Scope>
<IOProtocol>ap_fifo</IOProtocol>
<IOConfig></IOConfig>
<Dir>out</Dir>
<Bits>1</Bits>
<Attribute>control</Attribute>
</RtlPorts>
<RtlPorts>
<name>g2t_write_sid_V_V_dout</name>
<Object>g2t_write_sid_V_V</Object>
<Type>pointer</Type>
<Scope>global</Scope>
<IOProtocol>ap_fifo</IOProtocol>
<IOConfig></IOConfig>
<Dir>in</Dir>
<Bits>16</Bits>
<Attribute>data</Attribute>
</RtlPorts>
<RtlPorts>
<name>g2t_write_sid_V_V_empty_n</name>
<Object>g2t_write_sid_V_V</Object>
<Type>pointer</Type>
<Scope>global</Scope>
<IOProtocol>ap_fifo</IOProtocol>
<IOConfig></IOConfig>
<Dir>in</Dir>
<Bits>1</Bits>
<Attribute>control</Attribute>
</RtlPorts>
<RtlPorts>
<name>g2t_write_sid_V_V_read</name>
<Object>g2t_write_sid_V_V</Object>
<Type>pointer</Type>
<Scope>global</Scope>
<IOProtocol>ap_fifo</IOProtocol>
<IOConfig></IOConfig>
<Dir>out</Dir>
<Bits>1</Bits>
<Attribute>control</Attribute>
</RtlPorts>
<RtlPorts>
<name>g2t_read_sid_V_V_din</name>
<Object>g2t_read_sid_V_V</Object>
<Type>pointer</Type>
<Scope>global</Scope>
<IOProtocol>ap_fifo</IOProtocol>
<IOConfig></IOConfig>
<Dir>out</Dir>
<Bits>16</Bits>
<Attribute>data</Attribute>
</RtlPorts>
<RtlPorts>
<name>g2t_read_sid_V_V_full_n</name>
<Object>g2t_read_sid_V_V</Object>
<Type>pointer</Type>
<Scope>global</Scope>
<IOProtocol>ap_fifo</IOProtocol>
<IOConfig></IOConfig>
<Dir>in</Dir>
<Bits>1</Bits>
<Attribute>control</Attribute>
</RtlPorts>
<RtlPorts>
<name>g2t_read_sid_V_V_write</name>
<Object>g2t_read_sid_V_V</Object>
<Type>pointer</Type>
<Scope>global</Scope>
<IOProtocol>ap_fifo</IOProtocol>
<IOConfig></IOConfig>
<Dir>out</Dir>
<Bits>1</Bits>
<Attribute>control</Attribute>
</RtlPorts>
<RtlPorts>
<name>t2g_read_sid_V_V_din</name>
<Object>t2g_read_sid_V_V</Object>
<Type>pointer</Type>
<Scope>global</Scope>
<IOProtocol>ap_fifo</IOProtocol>
<IOConfig></IOConfig>
<Dir>out</Dir>
<Bits>16</Bits>
<Attribute>data</Attribute>
</RtlPorts>
<RtlPorts>
<name>t2g_read_sid_V_V_full_n</name>
<Object>t2g_read_sid_V_V</Object>
<Type>pointer</Type>
<Scope>global</Scope>
<IOProtocol>ap_fifo</IOProtocol>
<IOConfig></IOConfig>
<Dir>in</Dir>
<Bits>1</Bits>
<Attribute>control</Attribute>
</RtlPorts>
<RtlPorts>
<name>t2g_read_sid_V_V_write</name>
<Object>t2g_read_sid_V_V</Object>
<Type>pointer</Type>
<Scope>global</Scope>
<IOProtocol>ap_fifo</IOProtocol>
<IOConfig></IOConfig>
<Dir>out</Dir>
<Bits>1</Bits>
<Attribute>control</Attribute>
</RtlPorts>
</InterfaceSummary>
</Module>
<Module>
<Name>network_bridge_tcp</Name>
<PerformanceEstimates>
<SummaryOfTimingAnalysis>
<TargetClockPeriod>4.00</TargetClockPeriod>
<ClockUncertainty>0.50</ClockUncertainty>
<EstimatedClockPeriod>4.92</EstimatedClockPeriod>
</SummaryOfTimingAnalysis>
<SummaryOfOverallLatency>
<Best-caseLatency>8</Best-caseLatency>
<Average-caseLatency>8</Average-caseLatency>
<Worst-caseLatency>8</Worst-caseLatency>
<DataflowPipelineThroughput>1</DataflowPipelineThroughput>
<PipelineInitiationInterval>1</PipelineInitiationInterval>
<PipelineType>dataflow</PipelineType>
</SummaryOfOverallLatency>
</PerformanceEstimates>
<AreaEstimates>
<Resources>
<BRAM_18K>1</BRAM_18K>
<FF>1404</FF>
<LUT>1238</LUT>
<DSP48E>0</DSP48E>
</Resources>
</AreaEstimates>
<InterfaceSummary>
<RtlPorts>
<name>rxGalapagosBridge_V_dout</name>
<Object>rxGalapagosBridge_V</Object>
<Type>pointer</Type>
<Scope></Scope>
<IOProtocol>ap_fifo</IOProtocol>
<IOConfig></IOConfig>
<Dir>in</Dir>
<Bits>73</Bits>
<Attribute>data</Attribute>
<CType>int</CType>
</RtlPorts>
<RtlPorts>
<name>rxGalapagosBridge_V_empty_n</name>
<Object>rxGalapagosBridge_V</Object>
<Type>pointer</Type>
<Scope></Scope>
<IOProtocol>ap_fifo</IOProtocol>
<IOConfig></IOConfig>
<Dir>in</Dir>
<Bits>1</Bits>
<Attribute>control</Attribute>
<CType>int</CType>
</RtlPorts>
<RtlPorts>
<name>rxGalapagosBridge_V_read</name>
<Object>rxGalapagosBridge_V</Object>
<Type>pointer</Type>
<Scope></Scope>
<IOProtocol>ap_fifo</IOProtocol>
<IOConfig></IOConfig>
<Dir>out</Dir>
<Bits>1</Bits>
<Attribute>control</Attribute>
<CType>int</CType>
</RtlPorts>
<RtlPorts>
<name>txMetaData_V_din</name>
<Object>txMetaData_V</Object>
<Type>pointer</Type>
<Scope></Scope>
<IOProtocol>ap_fifo</IOProtocol>
<IOConfig></IOConfig>
<Dir>out</Dir>
<Bits>32</Bits>
<Attribute>data</Attribute>
<CType>int</CType>
</RtlPorts>
<RtlPorts>
<name>txMetaData_V_full_n</name>
<Object>txMetaData_V</Object>
<Type>pointer</Type>
<Scope></Scope>
<IOProtocol>ap_fifo</IOProtocol>
<IOConfig></IOConfig>
<Dir>in</Dir>
<Bits>1</Bits>
<Attribute>control</Attribute>
<CType>int</CType>
</RtlPorts>
<RtlPorts>
<name>txMetaData_V_write</name>
<Object>txMetaData_V</Object>
<Type>pointer</Type>
<Scope></Scope>
<IOProtocol>ap_fifo</IOProtocol>
<IOConfig></IOConfig>
<Dir>out</Dir>
<Bits>1</Bits>
<Attribute>control</Attribute>
<CType>int</CType>
</RtlPorts>
<RtlPorts>
<name>openConnection_V_din</name>
<Object>openConnection_V</Object>
<Type>pointer</Type>
<Scope></Scope>
<IOProtocol>ap_fifo</IOProtocol>
<IOConfig></IOConfig>
<Dir>out</Dir>
<Bits>48</Bits>
<Attribute>data</Attribute>
<CType>int</CType>
</RtlPorts>
<RtlPorts>
<name>openConnection_V_full_n</name>
<Object>openConnection_V</Object>
<Type>pointer</Type>
<Scope></Scope>
<IOProtocol>ap_fifo</IOProtocol>
<IOConfig></IOConfig>
<Dir>in</Dir>
<Bits>1</Bits>
<Attribute>control</Attribute>
<CType>int</CType>
</RtlPorts>
<RtlPorts>
<name>openConnection_V_write</name>
<Object>openConnection_V</Object>
<Type>pointer</Type>
<Scope></Scope>
<IOProtocol>ap_fifo</IOProtocol>
<IOConfig></IOConfig>
<Dir>out</Dir>
<Bits>1</Bits>
<Attribute>control</Attribute>
<CType>int</CType>
</RtlPorts>
<RtlPorts>
<name>openConStatus_V_dout</name>
<Object>openConStatus_V</Object>
<Type>pointer</Type>
<Scope></Scope>
<IOProtocol>ap_fifo</IOProtocol>
<IOConfig></IOConfig>
<Dir>in</Dir>
<Bits>17</Bits>
<Attribute>data</Attribute>
<CType>int</CType>
</RtlPorts>
<RtlPorts>
<name>openConStatus_V_empty_n</name>
<Object>openConStatus_V</Object>
<Type>pointer</Type>
<Scope></Scope>
<IOProtocol>ap_fifo</IOProtocol>
<IOConfig></IOConfig>
<Dir>in</Dir>
<Bits>1</Bits>
<Attribute>control</Attribute>
<CType>int</CType>
</RtlPorts>
<RtlPorts>
<name>openConStatus_V_read</name>
<Object>openConStatus_V</Object>
<Type>pointer</Type>
<Scope></Scope>
<IOProtocol>ap_fifo</IOProtocol>
<IOConfig></IOConfig>
<Dir>out</Dir>
<Bits>1</Bits>
<Attribute>control</Attribute>
<CType>int</CType>
</RtlPorts>
<RtlPorts>
<name>txData_V_din</name>
<Object>txData_V</Object>
<Type>pointer</Type>
<Scope></Scope>
<IOProtocol>ap_fifo</IOProtocol>
<IOConfig></IOConfig>
<Dir>out</Dir>
<Bits>73</Bits>
<Attribute>data</Attribute>
<CType>int</CType>
</RtlPorts>
<RtlPorts>
<name>txData_V_full_n</name>
<Object>txData_V</Object>
<Type>pointer</Type>
<Scope></Scope>
<IOProtocol>ap_fifo</IOProtocol>
<IOConfig></IOConfig>
<Dir>in</Dir>
<Bits>1</Bits>
<Attribute>control</Attribute>
<CType>int</CType>
</RtlPorts>
<RtlPorts>
<name>txData_V_write</name>
<Object>txData_V</Object>
<Type>pointer</Type>
<Scope></Scope>
<IOProtocol>ap_fifo</IOProtocol>
<IOConfig></IOConfig>
<Dir>out</Dir>
<Bits>1</Bits>
<Attribute>control</Attribute>
<CType>int</CType>
</RtlPorts>
<RtlPorts>
<name>txStatus_V_V_dout</name>
<Object>txStatus_V_V</Object>
<Type>pointer</Type>
<Scope></Scope>
<IOProtocol>ap_fifo</IOProtocol>
<IOConfig></IOConfig>
<Dir>in</Dir>
<Bits>17</Bits>
<Attribute>data</Attribute>
<CType>int</CType>
</RtlPorts>
<RtlPorts>
<name>txStatus_V_V_empty_n</name>
<Object>txStatus_V_V</Object>
<Type>pointer</Type>
<Scope></Scope>
<IOProtocol>ap_fifo</IOProtocol>
<IOConfig></IOConfig>
<Dir>in</Dir>
<Bits>1</Bits>
<Attribute>control</Attribute>
<CType>int</CType>
</RtlPorts>
<RtlPorts>
<name>txStatus_V_V_read</name>
<Object>txStatus_V_V</Object>
<Type>pointer</Type>
<Scope></Scope>
<IOProtocol>ap_fifo</IOProtocol>
<IOConfig></IOConfig>
<Dir>out</Dir>
<Bits>1</Bits>
<Attribute>control</Attribute>
<CType>int</CType>
</RtlPorts>
<RtlPorts>
<name>listenPort_V_V_din</name>
<Object>listenPort_V_V</Object>
<Type>pointer</Type>
<Scope></Scope>
<IOProtocol>ap_fifo</IOProtocol>
<IOConfig></IOConfig>
<Dir>out</Dir>
<Bits>16</Bits>
<Attribute>data</Attribute>
<CType>int</CType>
</RtlPorts>
<RtlPorts>
<name>listenPort_V_V_full_n</name>
<Object>listenPort_V_V</Object>
<Type>pointer</Type>
<Scope></Scope>
<IOProtocol>ap_fifo</IOProtocol>
<IOConfig></IOConfig>
<Dir>in</Dir>
<Bits>1</Bits>
<Attribute>control</Attribute>
<CType>int</CType>
</RtlPorts>
<RtlPorts>
<name>listenPort_V_V_write</name>
<Object>listenPort_V_V</Object>
<Type>pointer</Type>
<Scope></Scope>
<IOProtocol>ap_fifo</IOProtocol>
<IOConfig></IOConfig>
<Dir>out</Dir>
<Bits>1</Bits>
<Attribute>control</Attribute>
<CType>int</CType>
</RtlPorts>
<RtlPorts>
<name>listenPortStatus_V_dout</name>
<Object>listenPortStatus_V</Object>
<Type>pointer</Type>
<Scope></Scope>
<IOProtocol>ap_fifo</IOProtocol>
<IOConfig></IOConfig>
<Dir>in</Dir>
<Bits>1</Bits>
<Attribute>data</Attribute>
<CType>bool</CType>
</RtlPorts>
<RtlPorts>
<name>listenPortStatus_V_empty_n</name>
<Object>listenPortStatus_V</Object>
<Type>pointer</Type>
<Scope></Scope>
<IOProtocol>ap_fifo</IOProtocol>
<IOConfig></IOConfig>
<Dir>in</Dir>
<Bits>1</Bits>
<Attribute>control</Attribute>
<CType>bool</CType>
</RtlPorts>
<RtlPorts>
<name>listenPortStatus_V_read</name>
<Object>listenPortStatus_V</Object>
<Type>pointer</Type>
<Scope></Scope>
<IOProtocol>ap_fifo</IOProtocol>
<IOConfig></IOConfig>
<Dir>out</Dir>
<Bits>1</Bits>
<Attribute>control</Attribute>
<CType>bool</CType>
</RtlPorts>
<RtlPorts>
<name>notifications_V_dout</name>
<Object>notifications_V</Object>
<Type>pointer</Type>
<Scope></Scope>
<IOProtocol>ap_fifo</IOProtocol>
<IOConfig></IOConfig>
<Dir>in</Dir>
<Bits>81</Bits>
<Attribute>data</Attribute>
<CType>int</CType>
</RtlPorts>
<RtlPorts>
<name>notifications_V_empty_n</name>
<Object>notifications_V</Object>
<Type>pointer</Type>
<Scope></Scope>
<IOProtocol>ap_fifo</IOProtocol>
<IOConfig></IOConfig>
<Dir>in</Dir>
<Bits>1</Bits>
<Attribute>control</Attribute>
<CType>int</CType>
</RtlPorts>
<RtlPorts>
<name>notifications_V_read</name>
<Object>notifications_V</Object>
<Type>pointer</Type>
<Scope></Scope>
<IOProtocol>ap_fifo</IOProtocol>
<IOConfig></IOConfig>
<Dir>out</Dir>
<Bits>1</Bits>
<Attribute>control</Attribute>
<CType>int</CType>
</RtlPorts>
<RtlPorts>
<name>readRequest_V_din</name>
<Object>readRequest_V</Object>
<Type>pointer</Type>
<Scope></Scope>
<IOProtocol>ap_fifo</IOProtocol>
<IOConfig></IOConfig>
<Dir>out</Dir>
<Bits>32</Bits>
<Attribute>data</Attribute>
<CType>int</CType>
</RtlPorts>
<RtlPorts>
<name>readRequest_V_full_n</name>
<Object>readRequest_V</Object>
<Type>pointer</Type>
<Scope></Scope>
<IOProtocol>ap_fifo</IOProtocol>
<IOConfig></IOConfig>
<Dir>in</Dir>
<Bits>1</Bits>
<Attribute>control</Attribute>
<CType>int</CType>
</RtlPorts>
<RtlPorts>
<name>readRequest_V_write</name>
<Object>readRequest_V</Object>
<Type>pointer</Type>
<Scope></Scope>
<IOProtocol>ap_fifo</IOProtocol>
<IOConfig></IOConfig>
<Dir>out</Dir>
<Bits>1</Bits>
<Attribute>control</Attribute>
<CType>int</CType>
</RtlPorts>
<RtlPorts>
<name>rxMetaData_V_V_dout</name>
<Object>rxMetaData_V_V</Object>
<Type>pointer</Type>
<Scope></Scope>
<IOProtocol>ap_fifo</IOProtocol>
<IOConfig></IOConfig>
<Dir>in</Dir>
<Bits>16</Bits>
<Attribute>data</Attribute>
<CType>int</CType>
</RtlPorts>
<RtlPorts>
<name>rxMetaData_V_V_empty_n</name>
<Object>rxMetaData_V_V</Object>
<Type>pointer</Type>
<Scope></Scope>
<IOProtocol>ap_fifo</IOProtocol>
<IOConfig></IOConfig>
<Dir>in</Dir>
<Bits>1</Bits>
<Attribute>control</Attribute>
<CType>int</CType>
</RtlPorts>
<RtlPorts>
<name>rxMetaData_V_V_read</name>
<Object>rxMetaData_V_V</Object>
<Type>pointer</Type>
<Scope></Scope>
<IOProtocol>ap_fifo</IOProtocol>
<IOConfig></IOConfig>
<Dir>out</Dir>
<Bits>1</Bits>
<Attribute>control</Attribute>
<CType>int</CType>
</RtlPorts>
<RtlPorts>
<name>rxData_V_dout</name>
<Object>rxData_V</Object>
<Type>pointer</Type>
<Scope></Scope>
<IOProtocol>ap_fifo</IOProtocol>
<IOConfig></IOConfig>
<Dir>in</Dir>
<Bits>73</Bits>
<Attribute>data</Attribute>
<CType>int</CType>
</RtlPorts>
<RtlPorts>
<name>rxData_V_empty_n</name>
<Object>rxData_V</Object>
<Type>pointer</Type>
<Scope></Scope>
<IOProtocol>ap_fifo</IOProtocol>
<IOConfig></IOConfig>
<Dir>in</Dir>
<Bits>1</Bits>
<Attribute>control</Attribute>
<CType>int</CType>
</RtlPorts>
<RtlPorts>
<name>rxData_V_read</name>
<Object>rxData_V</Object>
<Type>pointer</Type>
<Scope></Scope>
<IOProtocol>ap_fifo</IOProtocol>
<IOConfig></IOConfig>
<Dir>out</Dir>
<Bits>1</Bits>
<Attribute>control</Attribute>
<CType>int</CType>
</RtlPorts>
<RtlPorts>
<name>txGalapagosBridge_V_din</name>
<Object>txGalapagosBridge_V</Object>
<Type>pointer</Type>
<Scope></Scope>
<IOProtocol>ap_fifo</IOProtocol>
<IOConfig></IOConfig>
<Dir>out</Dir>
<Bits>73</Bits>
<Attribute>data</Attribute>
<CType>int</CType>
</RtlPorts>
<RtlPorts>
<name>txGalapagosBridge_V_full_n</name>
<Object>txGalapagosBridge_V</Object>
<Type>pointer</Type>
<Scope></Scope>
<IOProtocol>ap_fifo</IOProtocol>
<IOConfig></IOConfig>
<Dir>in</Dir>
<Bits>1</Bits>
<Attribute>control</Attribute>
<CType>int</CType>
</RtlPorts>
<RtlPorts>
<name>txGalapagosBridge_V_write</name>
<Object>txGalapagosBridge_V</Object>
<Type>pointer</Type>
<Scope></Scope>
<IOProtocol>ap_fifo</IOProtocol>
<IOConfig></IOConfig>
<Dir>out</Dir>
<Bits>1</Bits>
<Attribute>control</Attribute>
<CType>int</CType>
</RtlPorts>
<RtlPorts>
<name>state_out_V</name>
<Object>state_out_V</Object>
<Type>pointer</Type>
<Scope></Scope>
<IOProtocol>ap_vld</IOProtocol>
<IOConfig></IOConfig>
<Dir>out</Dir>
<Bits>4</Bits>
<Attribute>data</Attribute>
<CType>int</CType>
</RtlPorts>
<RtlPorts>
<name>state_out_V_ap_vld</name>
<Object>state_out_V</Object>
<Type>pointer</Type>
<Scope></Scope>
<IOProtocol>ap_vld</IOProtocol>
<IOConfig></IOConfig>
<Dir>out</Dir>
<Bits>1</Bits>
<Attribute>control</Attribute>
<CType>int</CType>
</RtlPorts>
<RtlPorts>
<name>header_out_V</name>
<Object>header_out_V</Object>
<Type>pointer</Type>
<Scope></Scope>
<IOProtocol>ap_vld</IOProtocol>
<IOConfig></IOConfig>
<Dir>out</Dir>
<Bits>64</Bits>
<Attribute>data</Attribute>
<CType>int</CType>
</RtlPorts>
<RtlPorts>
<name>header_out_V_ap_vld</name>
<Object>header_out_V</Object>
<Type>pointer</Type>
<Scope></Scope>
<IOProtocol>ap_vld</IOProtocol>
<IOConfig></IOConfig>
<Dir>out</Dir>
<Bits>1</Bits>
<Attribute>control</Attribute>
<CType>int</CType>
</RtlPorts>
<RtlPorts>
<name>size_out_V</name>
<Object>size_out_V</Object>
<Type>pointer</Type>
<Scope></Scope>
<IOProtocol>ap_vld</IOProtocol>
<IOConfig></IOConfig>
<Dir>out</Dir>
<Bits>16</Bits>
<Attribute>data</Attribute>
<CType>int</CType>
</RtlPorts>
<RtlPorts>
<name>size_out_V_ap_vld</name>
<Object>size_out_V</Object>
<Type>pointer</Type>
<Scope></Scope>
<IOProtocol>ap_vld</IOProtocol>
<IOConfig></IOConfig>
<Dir>out</Dir>
<Bits>1</Bits>
<Attribute>control</Attribute>
<CType>int</CType>
</RtlPorts>
<RtlPorts>
<name>sessionID_out_V</name>
<Object>sessionID_out_V</Object>
<Type>pointer</Type>
<Scope></Scope>
<IOProtocol>ap_vld</IOProtocol>
<IOConfig></IOConfig>
<Dir>out</Dir>
<Bits>16</Bits>
<Attribute>data</Attribute>
<CType>int</CType>
</RtlPorts>
<RtlPorts>
<name>sessionID_out_V_ap_vld</name>
<Object>sessionID_out_V</Object>
<Type>pointer</Type>
<Scope></Scope>
<IOProtocol>ap_vld</IOProtocol>
<IOConfig></IOConfig>
<Dir>out</Dir>
<Bits>1</Bits>
<Attribute>control</Attribute>
<CType>int</CType>
</RtlPorts>
<RtlPorts>
<name>ip_table_V_address0</name>
<Object>ip_table_V</Object>
<Type>array</Type>
<Scope>global</Scope>
<IOProtocol>ap_memory</IOProtocol>
<IOConfig></IOConfig>
<Dir>out</Dir>
<Bits>8</Bits>
<Attribute>address</Attribute>
<CType>int</CType>
</RtlPorts>
<RtlPorts>
<name>ip_table_V_ce0</name>
<Object>ip_table_V</Object>
<Type>array</Type>
<Scope>global</Scope>
<IOProtocol>ap_memory</IOProtocol>
<IOConfig></IOConfig>
<Dir>out</Dir>
<Bits>1</Bits>
<Attribute>control</Attribute>
<CType>int</CType>
</RtlPorts>
<RtlPorts>
<name>ip_table_V_d0</name>
<Object>ip_table_V</Object>
<Type>array</Type>
<Scope>global</Scope>
<IOProtocol>ap_memory</IOProtocol>
<IOConfig></IOConfig>
<Dir>out</Dir>
<Bits>32</Bits>
<Attribute>data</Attribute>
<CType>int</CType>
</RtlPorts>
<RtlPorts>
<name>ip_table_V_q0</name>
<Object>ip_table_V</Object>
<Type>array</Type>
<Scope>global</Scope>
<IOProtocol>ap_memory</IOProtocol>
<IOConfig></IOConfig>
<Dir>in</Dir>
<Bits>32</Bits>
<Attribute>data</Attribute>
<CType>int</CType>
</RtlPorts>
<RtlPorts>
<name>ip_table_V_we0</name>
<Object>ip_table_V</Object>
<Type>array</Type>
<Scope>global</Scope>
<IOProtocol>ap_memory</IOProtocol>
<IOConfig></IOConfig>
<Dir>out</Dir>
<Bits>1</Bits>
<Attribute>control</Attribute>
<CType>int</CType>
</RtlPorts>
<RtlPorts>
<name>ip_table_V_address1</name>
<Object>ip_table_V</Object>
<Type>array</Type>
<Scope>global</Scope>
<IOProtocol>ap_memory</IOProtocol>
<IOConfig></IOConfig>
<Dir>out</Dir>
<Bits>8</Bits>
<Attribute>address</Attribute>
<CType>int</CType>
</RtlPorts>
<RtlPorts>
<name>ip_table_V_ce1</name>
<Object>ip_table_V</Object>
<Type>array</Type>
<Scope>global</Scope>
<IOProtocol>ap_memory</IOProtocol>
<IOConfig></IOConfig>
<Dir>out</Dir>
<Bits>1</Bits>
<Attribute>control</Attribute>
<CType>int</CType>
</RtlPorts>
<RtlPorts>
<name>ip_table_V_d1</name>
<Object>ip_table_V</Object>
<Type>array</Type>
<Scope>global</Scope>
<IOProtocol>ap_memory</IOProtocol>
<IOConfig></IOConfig>
<Dir>out</Dir>
<Bits>32</Bits>
<Attribute>data</Attribute>
<CType>int</CType>
</RtlPorts>
<RtlPorts>
<name>ip_table_V_q1</name>
<Object>ip_table_V</Object>
<Type>array</Type>
<Scope>global</Scope>
<IOProtocol>ap_memory</IOProtocol>
<IOConfig></IOConfig>
<Dir>in</Dir>
<Bits>32</Bits>
<Attribute>data</Attribute>
<CType>int</CType>
</RtlPorts>
<RtlPorts>
<name>ip_table_V_we1</name>
<Object>ip_table_V</Object>
<Type>array</Type>
<Scope>global</Scope>
<IOProtocol>ap_memory</IOProtocol>
<IOConfig></IOConfig>
<Dir>out</Dir>
<Bits>1</Bits>
<Attribute>control</Attribute>
<CType>int</CType>
</RtlPorts>
<RtlPorts>
<name>ap_clk</name>
<Object>network_bridge_tcp</Object>
<Type>return value</Type>
<Scope></Scope>
<IOProtocol>ap_ctrl_none</IOProtocol>
<IOConfig></IOConfig>
<Dir>in</Dir>
<Bits>1</Bits>
<Attribute>control</Attribute>
</RtlPorts>
<RtlPorts>
<name>ap_rst</name>
<Object>network_bridge_tcp</Object>
<Type>return value</Type>
<Scope></Scope>
<IOProtocol>ap_ctrl_none</IOProtocol>
<IOConfig></IOConfig>
<Dir>in</Dir>
<Bits>1</Bits>
<Attribute>control</Attribute>
</RtlPorts>
</InterfaceSummary>
</Module>
</ModuleInformation>

</profile>
